<?xml version="1.0" encoding="UTF-8"?>

<PublicEvent xmlns="http://data.europa.eu/m8g/xsd" 
    xmlns:dct="http://purl.org/dc/terms/" 
    xmlns:sawsdl="http://www.w3.org/ns/sawsdl" 
    xmlns:xsi="http://www.w3.org/2001/XMLSchema-instance" 
    xsi:schemaLocation="http://data.europa.eu/m8g/xsd ..\CoreVoc_Public_Event\CoreVoc_Public_Event.xsd">	
    
    <Accessibility xml:lang="">screen reader</Accessibility>
	<Address>
        <AddressArea xml:lang="fr">Province de Hainaut</AddressArea>
		<AdminUnitL1 xml:lang="fr">Belgique</AdminUnitL1>
		<AdminUnitL2 xml:lang="fr">Wallonie</AdminUnitL2>
		<FullAddress xml:lang="fr">55 Rue Gendebien, 6200 Châtelet</FullAddress>
		<LocatorDesignatorAddress>55</LocatorDesignatorAddress>
		<PostCode>6200</PostCode>
		<PostName xml:lang="fr">Châtelet</PostName>
	</Address>
	<Audience>Dummies</Audience>
	<ContactPoint>
		<HasEmail>info@unicef.be</HasEmail>
		<HasTelephone>+32 2 230 59 70</HasTelephone>
	</ContactPoint>
	<Description xml:lang="en">A special event</Description>
	<Description xml:lang="de">Ein besonderer Anlaß</Description>
	<EventNumber xml:lang="">4711</EventNumber>
	<EventStatus>CANCELLED</EventStatus>
	<EventType>TRAINING_WORKSHOP</EventType>
	<ExpectedNumberOfParticipants>3</ExpectedNumberOfParticipants>
	<Format>physical meeting</Format>
	<HasParticipation>
		<Description xml:lang="">very interesting workshop</Description>
		<HasParticipant>
            <AgentName xml:lang="fr">Service Public Fédéral FINANCES</AgentName>
            <AgentName xml:lang="nl">Federale Overheidsdiesnt FINANCIEN</AgentName>
            <AgentName xml:lang="en">Federal Public Service FINANCE</AgentName>

            <AgentType>Public Service</AgentType>
			<Address>
                <AdminUnitL1 xml:lang="fr">Belgique</AdminUnitL1>
                <AdminUnitL2 xml:lang="fr">Région de Bruxelles-Capitale</AdminUnitL2>
                <FullAddress xml:lang="fr">Rue Picard 7/306, 1000 Bruxelles, Belgique</FullAddress>
                <LocatorDesignatorAddress>7/30</LocatorDesignatorAddress>
                <PostCode>1000</PostCode>
                <PostName xml:lang="fr">Bruxelles</PostName>
                <Thoroughfare xml:lang="fr">Rue Picard</Thoroughfare>
			</Address>
			<Participates>
				<Description xml:lang="">Participation in which an Agent is involved</Description>
				<HasTime>
					<Description xml:lang="">The event occurs at intervals of every twelve hours.</Description>
					<Frequency>12HRS</Frequency>
				</HasTime>
				<Identifier>Participation-id 08/15</Identifier>
				<Role>Role-id 4711</Role>
			</Participates>
		</HasParticipant>
		<HasTime>
            <Description xml:lang="">The event occurs at intervals of every twelve hours.</Description>
            <Frequency>12HRS</Frequency>
		</HasTime>
	</HasParticipation>
	<Title xml:lang="">Public Events</Title>
	<Topic>All workshops you are interested in</Topic>
</PublicEvent>
